LICENSE
MANIFEST.in
README.rst
plunchy.py
setup.py
bin/plunchy
plunchy.egg-info/PKG-INFO
plunchy.egg-info/SOURCES.txt
plunchy.egg-info/dependency_links.txt
plunchy.egg-info/pbr.json
plunchy.egg-info/top_level.txt