Metadata-Version: 1.1
Name: plunchy
Version: 1.0.1
Summary: A simpler interface into OS X's launchctl
Home-page: https://github.com/epochblue/plunchy
Author: Bill Israel
Author-email: bill.israel@gmail.com
License: MIT
Keywords: os x,launchctl,lunchy
Platform: UNKNOWN
Classifier: Development Status :: 5 - Production/Stable
Classifier: Environment :: Console
Classifier: Environment :: MacOS X
Classifier: Intended Audience :: Developers
Classifier: Intended Audience :: Information Technology
Classifier: Intended Audience :: System Administrators
Classifier: License :: OSI Approved :: MIT License
Classifier: Operating System :: MacOS :: MacOS X
Classifier: Programming Language :: Python :: 2.7
Classifier: Programming Language :: Python :: 3
Classifier: Topic :: Utilities
